Metadata-Version: 1.0
Name: jcstarter
Version: 0.0.6
Summary: 大官人测试pip包
Home-page: http://mythyou.com
Author: daguanren
Author-email: jcsl12@163.com    
License: MIT Licence
Keywords: pip,jcs,daguanren,大官人
Platform: any
